[{"id":"d391e5da.18ec58","type":"mqtt-broker","broker":"test.mosquitto.org","port":"1883","clientid":""},{"id":"e6ae1a95.2a5288","type":"debug","name":"DebugPrint","active":true,"console":"false","complete":"payload","x":322.22222900390625,"y":74,"z":"5fc74541.d5102c","wires":[]},{"id":"4e2d0e0a.aa69f","type":"inject","name":"","topic":"","payload":"Hello!","payloadType":"string","repeat":"","crontab":"","once":false,"x":67.22222900390625,"y":203.11111450195312,"z":"5fc74541.d5102c","wires":[["e6ae1a95.2a5288","9beb2657.831488"]]},{"id":"9beb2657.831488","type":"mqtt out","name":"MQTT bluetooth device count","topic":"lora/bluetooth","qos":"0","retain":"false","broker":"d391e5da.18ec58","x":662,"y":37,"z":"5fc74541.d5102c","wires":[]},{"id":"ce8d8c59.e3f76","type":"function","name":"Parse lora packet","func":"var strArr = msg.payload.split(\",\")\nvar data = JSON.parse(JSON.stringify(strArr))\n// Necessary to create object wrappers because\n// MQTT nodes ask for the payload attribute\nvar devObj = {payload:data[0]}\nvar loudObj = {payload:data[1]}\nvar tempObj = {payload:data[2]}\nvar humObj = {payload:data[3]}\nreturn [devObj,loudObj,tempObj,humObj]\n","outputs":"4","noerr":0,"x":300,"y":262,"z":"5fc74541.d5102c","wires":[["9beb2657.831488","3a5f496c.38ba76"],["c19f1d39.9480d","7d08b6e1.992cc8"],["37ecb1b4.de1dee","339a2eed.063072"],["d1ba1674.e146e8","e988a662.394548"]]},{"id":"3a5f496c.38ba76","type":"debug","name":"devCount","active":true,"console":"false","complete":"payload","x":679,"y":71,"z":"5fc74541.d5102c","wires":[]},{"id":"176d858f.bb3b1a","type":"lora in","name":"Lora","datatype":"utf8","x":116,"y":85,"z":"5fc74541.d5102c","wires":[["e6ae1a95.2a5288","ce8d8c59.e3f76"]]},{"id":"37ecb1b4.de1dee","type":"mqtt out","name":"MQTT temperature","topic":"lora/temperature","qos":"0","retain":"false","broker":"d391e5da.18ec58","x":612,"y":211,"z":"5fc74541.d5102c","wires":[]},{"id":"c19f1d39.9480d","type":"mqtt out","name":"MQTT loudness","topic":"lora/loudness","qos":"0","retain":"false","broker":"d391e5da.18ec58","x":648,"y":129,"z":"5fc74541.d5102c","wires":[]},{"id":"d1ba1674.e146e8","type":"mqtt out","name":"MQTT humidity","topic":"lora/humidity","qos":"0","retain":"false","broker":"d391e5da.18ec58","x":623,"y":281,"z":"5fc74541.d5102c","wires":[]},{"id":"7d08b6e1.992cc8","type":"debug","name":"","active":true,"console":"false","complete":"false","x":730,"y":160,"z":"5fc74541.d5102c","wires":[]},{"id":"339a2eed.063072","type":"debug","name":"","active":true,"console":"false","complete":"false","x":632,"y":240,"z":"5fc74541.d5102c","wires":[]},{"id":"e988a662.394548","type":"debug","name":"","active":true,"console":"false","complete":"false","x":680,"y":315,"z":"5fc74541.d5102c","wires":[]}]
